{
    "backend" : [
        {
            "icon": "devicon-csharp-plain",
            "title": "C#",
            "text": ""
        },
        {
            "icon": "devicon-dot-net-plain-wordmark",
            "title": ".NET",
            "text": ""
        },
        {
            "icon": "devicon-microsoftsqlserver-plain",
            "title": "MS SQL Server",
            "text": ""
        },
        {
            "icon": "TEXT",
            "title": "API",
            "text": ""
        },
        {
            "icon": "devicon-cplusplus-plain",
            "title": "C++",
            "text": "Basic"
        },
        {
            "icon": "devicon-javascript-plain",
            "title": "JavaScript",
            "text": ""
        },
        {
            "icon": "devicon-react-plain",
            "title": "REACT",
            "text": ""
        },
        {
            "icon": "devicon-bootstrap-plain",
            "title": "Bootstrap",
            "text": ""
        }
    ]

}